Workbook

Sheet START
A1: City Budget Simulation — Module 1 Final
A3: You are managing a city budget over time.
A4: Your resources are limited. Your choices have consequences.
A6: Total Budget: 100 Units
A8: Use the menu above to begin.

Sheet CH1_SIM
A1: Chapter 1 — Building the City
A3: Starting Budget | B3: 100
A4: Remaining Budget | B4: =B3-B12 -> 65
A6: Choose which projects to fund. You cannot fund everything.
D7: Decision Table
D8: Project | E8: Cost (Units) | F8: Select | G8: City Impact
D9: Road Repairs | E9: 20 | F9: Yes | G9: 22
D10: School Improvements | E10: 30 | F10: No | G10: 27
D11: Emergency Services | E11: 25 | F11: No | G11: 24
A12: Total Units Used | B12: =SUMIF(F9:F13,"Yes",E9:E13) -> 35 | D12: Public Transportation | E12: 35 | G12: 35
D13: Parks & Recreation | E13: 15 | F13: Yes | G13: 10
D16: Actual Chapter 1 Impact | E16: =SUMIF(F8:F13,"Yes",E8:E13) -> 35
D17: Required Chapter 1 Impact | E17: 30
E18: =IF(E16>=E17,"OK","FAIL: City Stagnated in Chapter 1") -> OK

Sheet CH1_MCQ
A1: Chapter 1 Check — Economics Concepts
A3: Answer all questions before submitting.
A5: Q1. A city must choose between repairing roads or expanding public transit because it cannot afford both. Which economic idea explains why the city must choose?
A6: A) Incentives
A7: B) Budget constraint
A8: C) Marginal cost
A9: D) Revenue
A11: Q2. When a city chooses to fund schools instead of parks, what is the opportunity cost?
A12: A) The money spent on schools
A13: B) The park project that was not chosen
A14: C) Higher taxes
A15: D) Future penalties
... A36: D) A way to increase revenue

Sheet CH2_SIM
A1: Chapter 2 — Rising Costs
A3: Remaining Budget From Chapter 1 (Units): | B3: =CH1_SIM!$B$4 - $D$5 -> 65 | C3: Chapter 2 Remaining Budget | D3: =B3 - SUMIF(D8:D10,"Yes",C8:C10) -> 28.333333 | E3: =IF(D3<0,"FAIL: Budget Exceeded","OK") -> OK
A5: As more units are spent, each additional project becomes more expensive to manage.
A7: Project | B7: Base Cost | C7: Adjusted Cost | D7: Select | E7: City Impact
A8: Housing Repairs | B8: 20 | C8: =IF(D8="Yes", B8 + G$10/3, B8) -> 20 | D8: NO | E8: 30
A9: Water Systems | B9: 25 | C9: =IF(D9="Yes", B9 + G$10/3, B9) -> 36.666667 | D9: YES | E9: 40
A10: Public Safety Tech | B10: 30 | C10: =IF(D10="Yes", B10 + G$10/3, B10) -> 30 | D10: NO | E10: 50 | G10: =100 - B3 -> 35
D12: Total City Impact From Chapter 2 | E12: =SUMIF(D8:D10,"Yes",E8:E10) -> 40
D13: Required Impact Chapter 2 | E13: 40
D15: TOTAL IMPACT FROM BOTH CHAPTERS | E15: =CH1_SIM!E16 + E12 -> 75
D16: Required Total Impact | E16: 70
E17: =IF(E15>=E16,"OK","FAIL: City Did Not Improve Enough") -> OK
F25: Sim Passed?

Sheet CH2_MCQ
A1: Chapter 2 Check — Marginal Cost, Incentives, and Penalties
A3: Answer all questions. You must score at least 4 out of 5 to continue.
A5: Q1. A city notices that each additional project it approves becomes harder and more expensive to manage than earlier projects. Which economic concept best explains this?
A6: A) Budget constraint
A7: B) Opportunity cost
A8: C) Marginal cost
A9: D) Revenue
A11: Q2. Why might a system intentionally make later decisions more expensive than earlier ones?
A12: A) To punish decision-makers
A13: B) To change behavior and encourage planning
A14: C) Because money disappears
A15: D) To reward spending
... A36: D) Total cost predicts revenue

Sheet CH3_SIM
A1: Chapter 3 — Planning Ahead | C1: Budget From Ch. 2 | D1: =CH2_SIM!D3 -> 28.333333
C2: Final Budget Left | D2: =D1-C11 -> 3.3333333 | E2: =IF(D11<0,"FAIL BUDGET","PASS BUDGET") -> PASS BUDGET
A3: Choose ONE option for the city’s future.
A6: Option | B6: Cost (Units) | C6: Select | D6: City Impact
A7: Emergency Reserve | B7: 20 | C7: NO | D7: 20
A8: Long-Term Infrastructure | B8: 30 | C8: NO | D8: 45
A9: Short-Term Improvements | B9: 25 | C9: YES | D9: 30
B11: Chapter 3 Cost | C11: =SUMIF(C7:C9,"Yes",B7:B9) -> 25 | D11: Chapter 3 Impact | E11: =SUMIF(C7:C9,"Yes",D7:D9) -> 30
D13: Total City Impact | E13: =E11+CH2_SIM!E15 -> 105
E14: =IF(E13>100,"City Impact Passed","City Impact Failed)") -> City Impact Passed

Sheet CH3_MCQ
A1: Chapter 3 Check — Tradeoffs and Option Value
A3: Answer all questions. You must score at least 4 out of 5 to continue.
A5: Q1:A city delays choosing a large project even though it looks beneficial right now. Why might this be a smart decision?
A6: A) It lowers total spending
A7: B) It avoids opportunity cost
A8: C) It keeps future choices available
A9: D) It increases revenue
A11: Q2. When a city commits all of its budget to one project, what does it lose most?
A12: A) Effiecency
A13: B) Flexibility
A14: C) Incentives
A15: D) Marginal Cost
... A36: D) Waiting for more information

Sheet FINAL_CHECK
A1: Final Economics Check — All Concepts
A2: You must score at least 3 out of 5 to earn a claim code.
A5: Q1. Which concept explains why choosing one option automatically means giving up another?
A6: A) Incentives
A7: B) Opportunity cost
A8: C) Revenue
A9: D) Progressive penalties
A11: Q2. Which concept focuses on the cost of making one additional decision?
A12: A) Budget constraint
A13: B) Total cost
A14: C) Marginal cost
A15: D) Option value
... A36: D) Progressive penalties

Sheet RESULTS
A1: Final Results | B1: Content
A3: Simulation Score (35%) | B3: =IF(AND(CH3_SIM!E2="PASS BUDGET", CH3_SIM!E14="City Impact Passed"), "SIMULATION PASSED", "SIMULATION FAILED") -> SIMULATION PASSED
A4: MCQ Score (65%) | B4: formula

Sheet SYSTEM_LOG
A1: Key | B1: Value | C1: Section | D1: Item | E1: Data
A2: STATUS | B2: NOT_STARTED
A3: TOTAL_UNITS | B3: 100
A4: REMAINING_UNITS | B4: 100
A5: SIM_SCORE | B5: 0
A6: MCQ_SCORE | B6: 0
A7: FINAL_SCORE | B7: 0
A8: CLAIM_CODE
C10: CH1_MCQ | D10: Q1 | E10: B
C11: CH1_MCQ | D11: Q2 | E11: B
C12: CH1_MCQ | D12: Q3 | E12: C
C13: CH1_MCQ | D13: Q4 | E13: B
C14: CH1_MCQ | D14: Q5 | E14: B
C15: CH2_MCQ | D15: Q1 | E15: C
C16: CH2_MCQ | D16: Q2 | E16: B
C17: CH2_MCQ | D17: Q3 | E17: C
C18: CH2_MCQ | D18: Q4 | E18: C
C19: CH2_MCQ | D19: Q5 | E19: B
C25: CH3_MCQ | D25: Q1 | E25: C
C26: CH3_MCQ | D26: Q2 | E26: B
... C29: CH3_MCQ | D29: Q5 | E29: B
